Metadata-Version: 1.0
Name: robotframework-step-library
Version: 0.1.0
Summary: Robot Framework Library for marking step in a test case
Home-page: https://github.com/rey5137/robot-runner-plugin
Author: Rey Pham
Author-email: pea5137@gmail.com
License: Apache License, Version 2.0
Platform: UNKNOWN
